ecraspay_django/__init__.py
ecraspay_django/admin.py
ecraspay_django/app.py
ecraspay_django/choices.py
ecraspay_django/models.py
ecraspay_django/serializers.py
ecraspay_django/services.py
ecraspay_django/settings.py
ecraspay_django/signals.py
ecraspay_django/urls.py
ecraspay_django/utils.py
ecraspay_django/views.py
ecraspay_django-0.1.1.dist-info/LICENSE
ecraspay_django-0.1.1.dist-info/METADATA
ecraspay_django-0.1.1.dist-info/WHEEL
ecraspay_django-0.1.1.dist-info/top_level.txt
ecraspay_django-0.1.1.dist-info/RECORD
