Metadata-Version: 2.1
Name: ecraspay-django
Version: 0.1.1
Summary: A Django integration for the ECRAS API.
Home-page: http://github.com/thelimeskies/ecraspay-sdk/src/python-django
Author: Asikhalaye Samuel
Author-email: sammyboy.as@gmail.com
Classifier: Programming Language :: Python :: 3
Classifier: License :: OSI Approved :: MIT License
Classifier: Operating System :: OS Independent
Classifier: Topic :: Software Development :: Libraries :: Python Modules
Classifier: Topic :: Software Development :: Libraries :: Application Frameworks
Classifier: Topic :: Software Development :: Libraries :: Python Modules
Classifier: Programming Language :: Python
Classifier: Programming Language :: Python :: 3
Classifier: Programming Language :: Python :: 3.6
Requires-Python: >=3.6
License-File: LICENSE
Requires-Dist: ecraspay-py>=0.1.0
Requires-Dist: requests>=2.32.3
Requires-Dist: pycryptodome>=3.11.0
Requires-Dist: Django>=3.2.8
